kshimotestpkg/__init__.py
kshimotestpkg/hello.py
kshimotestpkg-0.0.4.dist-info/METADATA
kshimotestpkg-0.0.4.dist-info/WHEEL
kshimotestpkg-0.0.4.dist-info/top_level.txt
kshimotestpkg-0.0.4.dist-info/RECORD
