Metadata-Version: 2.4
Name: kshimotestpkg
Version: 0.0.4
Summary: A basic hello package
Author: Christopher Kazu Shimotake
Author-email: <chris.shimotake@gmail.com>
Keywords: python
Classifier: Development Status :: 1 - Planning
Classifier: Intended Audience :: Developers
Classifier: Programming Language :: Python :: 3
Classifier: Operating System :: Unix
Classifier: Operating System :: MacOS :: MacOS X
Classifier: Operating System :: Microsoft :: Windows
Dynamic: author
Dynamic: author-email
Dynamic: classifier
Dynamic: keywords
Dynamic: summary
